Workbook

Sheet Lisez-moi
B2: Consultant agent IA — étude de rentabilité v2
B3: Déploiement d'agents IA + abonnement mensuel récurrent · projection 01/2027 → 01/2030
B5: Comment utiliser ce classeur
B6: 1. Ouvrez l'onglet « Paramètres ». C'est la seule feuille où vous saisissez des valeurs.
B7: 2. Les cellules à fond crème de la colonne C sont modifiables. Tout le reste est calculé.
B8: 3. Toutes les autres feuilles se recalculent automatiquement : hypothèses, MRR mensuel,
B9: synthèse annuelle, jalons, sensibilité, scénarios et graphiques.
B10: 4. Aucune valeur n'est figée en dur ailleurs que dans « Paramètres ».
B12: Le modèle en une phrase
B13: Un diagnostic gratuit chaque semaine, converti une fois sur deux en déploiement d'agent IA
B14: facturé 997 €, suivi d'un abonnement de 185 € par mois tant que l'agent reste en production.
B15: Le diagnostic non converti est le coût du modèle : du temps, jamais d'argent.
... B35: Version HTML interactive de la même étude : index.html du dépôt « consultant ».

Sheet Paramètres
B2: Paramètres du modèle
B3: Seules les cellules à fond crème sont à modifier. Tout le classeur se recalcule.
B5: Offre & tarification
B6: Paramètre | C6: Valeur | D6: Unité | E6: Défaut | F6: Rôle dans le modèle
B7: Prix abonnement mensuel (MRR par client) | C7: 185 | D7: €/mois | E7: 185 | F7: Facturé chaque mois tant que l'agent est en production.
B8: Prix de la prestation de déploiement | C8: 997 | D8: € | E8: 997 | F8: Ticket d'entrée, facturé une seule fois après la semaine de test.
B9: Jours de travail par déploiement | C9: 2 | D9: j | E9: 2 | F9: Temps d'implémentation d'un agent (ex. OCR devis vers base de données).
B11: Acquisition commerciale
B12: Paramètre | C12: Valeur | D12: Unité | E12: Défaut | F12: Rôle dans le modèle
B13: Diagnostics gratuits par semaine | C13: 1 | D13: /sem | E13: 1 | F13: Offre d'appel. Le volume de diagnostics pilote tout l'entonnoir.
B14: Durée d'un diagnostic | C14: 1 | D14: h | E14: 1 | F14: Temps consommé par diagnostic, converti ou non.
B15: Taux de conversion diagnostic vers déploiement | C15: 0.5 | D15: % | E15: 0.5 | F15: Part des diagnostics qui débouchent sur un déploiement payé.
B16: Jours de marketing / prospection par semaine | C16: 1 | D16: j/sem | E16: 1 | F16: Contenu, réseau, démarchage : le carburant des diagnostics.
B17: Taux de rétention annuel des abonnements | C17: 0.85 | D17: % | E17: 0.85 | F17: Part des clients encore abonnés 12 mois plus tard.
B19: Temps & capacité
B20: Paramètre | C20: Valeur | D20: Unité | E20: Défaut | F20: Rôle dans le modèle
B21: Jours travaillés par an (base 5 j/semaine) | C21: 208 | D21: j/an | E21: 208 | F21: 208 j = 41,6 semaines de 5 jours.
B22: Heures de travail par jour | C22: 7 | D22: h/j | E22: 7 | F22: Base de conversion jours vers heures.
B23: Heures/jour disponibles pour l'agent IA | C23: 3 | D23: h/j | E23: 3 | F23: Capacité réelle, hors salariat et vie personnelle.
B25: Salariat Naval Group
B26: Paramètre | C26: Valeur | D26: Unité | E26: Défaut | F26: Rôle dans le modèle
B27: Salaire net mensuel (avant IR) | C27: 3400 | D27: €/mois | E27: 3400 | F27: Salaire net versé, avant prélèvement à la source.
B28: Part du salaire conservée après IR | C28: 0.9 | D28: % | E28: 0.9 | F28: 90 % correspond à 10 % de prélèvement à la source.
B29: Jours travaillés par semaine (temps partiel) | C29: 4 | D29: j/sem | E29: 4 | F29: Contrat à temps partiel.
B30: Heures de présence par jour | C30: 8 | D30: h/j | E30: 8 | F30: Temps de présence contractuel.
B31: Heures de travail cérébral réel par jour | C31: 3 | D31: h/j | E31: 3 | F31: Production intellectuelle effective.
B32: Semaines travaillées par an | C32: 44 | D32: sem/an | E32: 44 | F32: 52 semaines moins congés et RTT.
B33: Jours de télétravail par semaine | C33: 1 | D33: j/sem | E33: 1 | F33: Déduits des jours de présence sur site.
B35: Fiscalité & train de vie
B36: Paramètre | C36: Valeur | D36: Unité | E36: Défaut | F36: Rôle dans le modèle
B37: Part du CA consultant conservée (net IR) | C37: 0.5 | D37: % | E37: 0.5 | F37: Cotisations + impôt sur le revenu + frais d'API des agents IA.
B38: Dépenses personnelles mensuelles | C38: 1800 | D38: €/mois | E38: 1800 | F38: Train de vie complet. Sert au calcul de l'épargne.
B40: Horizon de projection
B41: Paramètre | C41: Valeur | D41: Unité | E41: Défaut | F41: Rôle dans le modèle
B42: Année du premier mois projeté | C42: 2027 | E42: 2027 | F42: Le tableau MRR démarre à ce mois et couvre 37 mois.
B43: Mois du premier mois projeté (1 = janvier) | C43: 1 | E43: 1 | F43: 1 pour janvier. Le tableau va jusqu'à 01/2030 avec les valeurs par défaut.
B45: Colonne « Défaut » : valeur d'origine de l'étude, conservée pour référence.

Sheet Résultats clés
B2: Résultats clés
B3: Synthèse de l'étude. Toutes les valeurs découlent de la feuille Paramètres.
B5: Sur l'horizon complet (37 mois) | E5: Valeur d'un client
B6: MRR au dernier mois projeté | C6: ='MRR mensuel'!$F$40 | E6: Euros facturés par jour | F6: ='Unit economics'!$C$7
B7: ARR au dernier mois projeté | C7: ='MRR mensuel'!$F$40*12 | E7: Euros par heure facturée | F7: ='Unit economics'!$C$8
B8: Clients actifs au dernier mois | C8: ='MRR mensuel'!$D$40 | E8: Euros/h net IR (implémentation) | F8: ='Unit economics'!$C$9
B9: Revenu total net du dernier mois | C9: ='MRR mensuel'!$L$40 | E9: Revenu par client la première année | F9: ='Unit economics'!$C$25
B10: CA total cumulé | C10: ='MRR mensuel'!$N$40 | E10: Euros/h net IR la première année | F10: ='Unit economics'!$C$28
B11: Net consultant cumulé | C11: ='MRR mensuel'!$N$40*'Paramètres'!$C$37 | E11: LTV nette par client | F11: ='Unit economics'!$C$30
B12: Épargne cumulée | C12: ='MRR mensuel'!$O$40 | E12: Durée de vie d'un abonnement | F12: ='Hypothèses'!$C$35
B14: Charge de travail | E14: Deuxième année
B15: Heures annuelles sur le business | C15: ='Hypothèses'!$C$20 | E15: Clients en fin d'exercice | F15: ='Synthèse annuelle'!$L$6
B16: Heures hebdomadaires | C16: ='Hypothèses'!$C$22 | E16: MRR généré sur l'année | F16: ='Synthèse annuelle'!$D$6
B17: Jours équivalents travaillés par semaine | C17: ='Hypothèses'!$C$23 | E17: MRR net d'IR | F17: ='Synthèse annuelle'!$D$6*'Paramètres'!$C$37
B18: Taux de charge (charge / capacité) | C18: ='Hypothèses'!$C$27 | E18: Net consultant mensuel moyen | F18: ='Synthèse annuelle'!$G$6/12
B19: Part du temps à prospecter | C19: ='Hypothèses'!$C$29 | E19: Revenu mensuel consultant + salariat | F19: ='Synthèse annuelle'!$I$6/12
B20: Charge combinée avec le salariat | C20: ='Temps & capacité'!$C$31 | E20: Liquidités mensuelles après dépenses | F20: ='Synthèse annuelle'!$K$6/12
E21: Liquidités ajoutées sur l'année | F21: ='Synthèse annuelle'!$K$6
B22: Entonnoir annuel | E22: Euros/h équivalent agent IA | F22: ='Synthèse annuelle'!$O$6
B23: Diagnostics gratuits par an | C23: ='Hypothèses'!$C$8
B24: Automatisations vendues par semaine | C24: ='Hypothèses'!$C$10 | E24: Régime permanent
B25: Automatisations vendues par an | C25: ='Hypothèses'!$C$9 | E25: Clients au plateau | F25: ='Hypothèses'!$C$36
B26: Nouveaux clients par mois | C26: ='Hypothèses'!$C$11 | E26: MRR au plateau | F26: ='Hypothèses'!$C$37
B27: CA de déploiement annuel | C27: ='Hypothèses'!$C$12 | E27: CA annuel au plateau | F27: ='Hypothèses'!$C$38
E28: Net IR annuel au plateau | F28: ='Hypothèses'!$C$39
E29: Euros/h net au plateau | F29: ='Hypothèses'!$C$39/'Hypothèses'!$C$20

Sheet Hypothèses
B2: Hypothèses dérivées
B3: Tout est calculé à partir de la feuille Paramètres. Aucune saisie ici.
B5: Entonnoir commercial
B6: Indicateur | C6: Valeur | D6: Unité | E6: Formule
B7: Semaines travaillées par an | C7: ='Paramètres'!$C$21/5 | D7: sem | E7: jours_travaillés / 5
B8: Diagnostics gratuits par an | C8: ='Paramètres'!$C$13*'Hypothèses'!$C$7 | D8: /an | E8: diagnostics_semaine × semaines
B9: Automatisations vendues par an | C9: ='Hypothèses'!$C$8*'Paramètres'!$C$15 | D9: /an | E9: diagnostics_an × taux_conversion
B10: Automatisations vendues par semaine | C10: ='Paramètres'!$C$13*'Paramètres'!$C$15 | D10: /sem | E10: diagnostics_semaine × taux_conversion
B11: Nouveaux clients par mois | C11: ='Hypothèses'!$C$9/12 | D11: /mois | E11: clients_an / 12
B12: CA de déploiement annuel | C12: ='Hypothèses'!$C$9*'Paramètres'!$C$8 | D12: €/an | E12: clients_an × prix_déploiement
B14: Charge horaire de l'activité
B15: Indicateur | C15: Valeur | D15: Unité | E15: Formule
B16: Heures par automatisation | C16: ='Paramètres'!$C$9*'Paramètres'!$C$22 | D16: h | E16: jours_déploiement × heures_par_jour
B17: Heures de diagnostic par an | C17: ='Hypothèses'!$C$8*'Paramètres'!$C$14 | D17: h/an | E17: diagnostics_an × durée_diagnostic
B18: Heures de déploiement par an | C18: ='Hypothèses'!$C$9*'Hypothèses'!$C$16 | D18: h/an | E18: clients_an × heures_par_automatisation
B19: Heures de marketing par an | C19: ='Paramètres'!$C$16*'Hypothèses'!$C$7*'Paramètres'!$C$22 | D19: h/an | E19: jours_marketing × semaines × heures_par_jour
B20: Heures totales par an | C20: ='Hypothèses'!$C$17+'Hypothèses'!$C$18+'Hypothèses'!$C$19 | D20: h/an | E20: diagnostic + déploiement + marketing
B21: Heures hors marketing par an | C21: ='Hypothèses'!$C$17+'Hypothèses'!$C$18 | D21: h/an | E21: diagnostic + déploiement
B22: Heures hebdomadaires sur le business | C22: ='Hypothèses'!$C$20/'Hypothèses'!$C$7 | D22: h/sem | E22: heures_total / semaines
B23: Jours équivalents travaillés par semaine | C23: ='Hypothèses'!$C$22/'Paramètres'!$C$22 | D23: j/sem | E23: heures_hebdo / heures_par_jour
B24: Jours équivalents travaillés par an | C24: ='Hypothèses'!$C$20/'Paramètres'!$C$22 | D24: j/an | E24: heures_total_an / heures_par_jour
B25: Capacité annuelle déclarée | C25: ='Paramètres'!$C$21*'Paramètres'!$C$23 | D25: h/an | E25: jours_travaillés × heures_dispo_par_jour
B26: Heures disponibles théoriques (plein temps) | C26: ='Paramètres'!$C$21*'Paramètres'!$C$22 | D26: h/an | E26: jours_travaillés × heures_par_jour
B27: Taux de charge (charge / capacité) | C27: ='Hypothèses'!$C$20/'Hypothèses'!$C$25 | D27: % | E27: 100 % = capacité exactement saturée
B28: Heures réellement nécessaires par jour | C28: ='Hypothèses'!$C$20/'Paramètres'!$C$21 | D28: h/j | E28: heures_total_an / jours_travaillés
B29: Part du temps à prospecter, pas à implémenter | C29: =('Hypothèses'!$C$17+'Hypothèses'!$C$19)/'Hypothèses'!$C$20 | D29: % | E29: (diagnostic + marketing) / total
B31: Rétention et récurrence
B32: Indicateur | C32: Valeur | D32: Unité | E32: Formule
B33: Churn mensuel équivalent | C33: =1-'Paramètres'!$C$17^(1/12) | D33: %/mois | E33: 1 − rétention_annuelle^(1/12)
B34: Survie mensuelle | C34: =1-'Hypothèses'!$C$33 | D34: % | E34: 1 − churn_mensuel
B35: Durée de vie moyenne d'un abonnement | C35: =1/'Hypothèses'!$C$33 | D35: mois | E35: 1 / churn_mensuel
B36: Clients au plateau (entrées = churn) | C36: ='Hypothèses'!$C$11/'Hypothèses'!$C$33 | D36: clients | E36: nouveaux_mois / churn_mensuel
B37: MRR au plateau | C37: ='Hypothèses'!$C$36*'Paramètres'!$C$7 | D37: €/mois | E37: clients_plateau × prix_abonnement
B38: CA annuel au plateau | C38: ='Hypothèses'!$C$37*12+'Hypothèses'!$C$12 | D38: €/an | E38: MRR_plateau × 12 + CA_déploiement_an
B39: Net IR annuel au plateau | C39: ='Hypothèses'!$C$38*'Paramètres'!$C$37 | D39: €/an | E39: CA_plateau × taux_net_IR
B41: Salariat
B42: Indicateur | C42: Valeur | D42: Unité | E42: Formule
B43: Salaire mensuel net d'IR | C43: ='Paramètres'!$C$27*'Paramètres'!$C$28 | D43: €/mois | E43: salaire × taux_net_IR_salaire
B44: Salaire annuel net d'IR | C44: ='Hypothèses'!$C$43*12 | D44: €/an | E44: salaire_net_mensuel × 12
B45: Salaire annuel net avant IR | C45: ='Paramètres'!$C$27*12 | D45: €/an | E45: salaire × 12

Sheet Temps & capacité
B2: Temps & capacité
B3: Le modèle tient-il physiquement, à côté du salariat ?
B5: Socle salarié
B6: Indicateur | C6: Valeur | D6: Unité | E6: Formule
B7: Heures hebdomadaires de temps de présence | C7: ='Paramètres'!$C$29*'Paramètres'!$C$30 | D7: h/sem | E7: jours_semaine × heures_présence_jour
B8: Heures hebdomadaires de travail cérébral | C8: ='Paramètres'!$C$29*'Paramètres'!$C$31 | D8: h/sem | E8: jours_semaine × heures_cérébral_jour
B9: Heures annuelles de présence | C9: ='Temps & capacité'!$C$7*'Paramètres'!$C$32 | D9: h/an | E9: heures_présence_hebdo × semaines
B10: Heures annuelles de travail cérébral | C10: ='Temps & capacité'!$C$8*'Paramètres'!$C$32 | D10: h/an | E10: heures_cérébral_hebdo × semaines
B11: Jours annuels travaillés à temps partiel | C11: ='Paramètres'!$C$29*'Paramètres'!$C$32 | D11: j/an | E11: jours_semaine × semaines
B12: Jours sur site par an (hors télétravail) | C12: =('Paramètres'!$C$29-'Paramètres'!$C$33)*'Paramètres'!$C$32 | D12: j/an | E12: (jours_semaine − télétravail) × semaines
B13: Heures de travail réel par jour de présence | C13: ='Paramètres'!$C$31 | D13: h/j | E13: paramètre direct
B14: Intensité : travail réel / présence | C14: ='Temps & capacité'!$C$10/'Temps & capacité'!$C$9 | D14: % | E14: heures_cérébral / heures_présence
B15: Marge cognitive annuelle disponible | C15: ='Temps & capacité'!$C$9-'Temps & capacité'!$C$10 | D15: h/an | E15: présence − travail cérébral
B16: Net IR par heure de présence | C16: ='Hypothèses'!$C$44/'Temps & capacité'!$C$9 | D16: €/h | E16: salaire_net_annuel / heures_présence
B17: Net IR par heure de travail réel | C17: ='Hypothèses'!$C$44/'Temps & capacité'!$C$10 | D17: €/h | E17: salaire_net_annuel / heures_cérébral
B19: Capacité consultant
B20: Indicateur | C20: Valeur | D20: Unité | E20: Formule
B21: Jours travaillés par an | C21: ='Paramètres'!$C$21 | D21: j/an | E21: paramètre
B22: Semaines travaillées par an | C22: ='Hypothèses'!$C$7 | D22: sem | E22: jours_travaillés / 5
B23: Heures disponibles de travail sur l'année | C23: ='Hypothèses'!$C$26 | D23: h/an | E23: jours × heures_par_jour
B24: Heures réellement nécessaires par jour | C24: ='Hypothèses'!$C$28 | D24: h/j | E24: charge / jours_travaillés
B25: Heures annuelles consacrées à l'agent IA | C25: ='Hypothèses'!$C$20 | D25: h/an | E25: diagnostic + déploiement + marketing
B26: Heures hebdomadaires sur le business | C26: ='Hypothèses'!$C$22 | D26: h/sem | E26: charge annuelle / semaines
B27: Jours équivalents travaillés par semaine | C27: ='Hypothèses'!$C$23 | D27: j/sem | E27: heures_hebdo / heures_par_jour
B28: Heures réellement travaillées hors marketing | C28: ='Hypothèses'!$C$21 | D28: h/an | E28: diagnostic + déploiement
B29: Part du temps à prospecter, pas à implémenter | C29: ='Hypothèses'!$C$29 | D29: % | E29: (diagnostic + marketing) / total
B30: Taux de charge (charge / capacité déclarée) | C30: ='Hypothèses'!$C$27 | D30: % | E30: 100 % = capacité saturée
B31: Charge combinée salariat + business, par semaine | C31: ='Temps & capacité'!$C$7+'Hypothèses'!$C$22 | D31: h/sem | E31: présence salariée + business
B32: Charge combinée annuelle | C32: ='Temps & capacité'!$C$9+'Hypothèses'!$C$20 | D32: h/an | E32: présence annuelle + charge annuelle
B34: Répartition annuelle des heures
B35: Déploiements | C35: ='Hypothèses'!$C$18
B36: Marketing / prospection | C36: ='Hypothèses'!$C$19
B37: Diagnostics gratuits | C37: ='Hypothèses'!$C$17
B39: Présence annuelle | C39: ='Temps & capacité'!$C$9
B40: Travail cérébral | C40: ='Temps & capacité'!$C$10
B41: Business consultant | C41: ='Hypothèses'!$C$20

Sheet Unit economics
B2: Unit economics
B3: Ce que rapporte un client, heure par heure.
B5: Tarification et rendement horaire
B6: Indicateur | C6: Valeur | D6: Unité | E6: Formule
B7: Euros facturés par jour en tant que consultant | C7: ='Paramètres'!$C$8/'Paramètres'!$C$9 | D7: €/j | E7: prix_déploiement / jours_déploiement
B8: Euros par heure facturée en tant que consultant | C8: ='Paramètres'!$C$8/'Hypothèses'!$C$16 | D8: €/h | E8: prix_déploiement / heures_par_automatisation
B9: Euros/h net IR travaillés en tant que consultant IA | C9: ='Unit economics'!$C$8*'Paramètres'!$C$37 | D9: €/h | E9: CA_horaire × taux_net_IR
B10: Euros/jour net IR | C10: ='Unit economics'!$C$7*'Paramètres'!$C$37 | D10: €/j | E10: CA_journalier × taux_net_IR
B12: Par automatisation vendue
B13: Indicateur | C13: Valeur | D13: Unité | E13: Formule
B14: Euros par automatisation de base | C14: ='Paramètres'!$C$8 | D14: € | E14: paramètre
B15: Heures travaillées par automatisation de base | C15: ='Hypothèses'!$C$16 | D15: h | E15: jours_déploiement × heures_par_jour
B16: Heures de prospection amorties par vente | C16: ='Paramètres'!$C$14/'Paramètres'!$C$15 | D16: h | E16: durée_diagnostic / taux_conversion
B17: Heures totales investies par client | C17: ='Hypothèses'!$C$20/'Hypothèses'!$C$9 | D17: h | E17: heures_annuelles / clients_annuels
B18: Euros de MRR mensuel par automatisation | C18: ='Paramètres'!$C$7 | D18: €/mois | E18: paramètre
B20: Valeur du client
B21: Indicateur | C21: Valeur | D21: Unité | E21: Formule
B22: Euros de MRR annuel par client | C22: ='Paramètres'!$C$7*12 | D22: €/an | E22: prix_abonnement × 12
B23: Mois réellement payés sur 12 (avec churn) | C23: ='Hypothèses'!$C$34*(1-'Hypothèses'!$C$34^12)/'Hypothèses'!$C$33 | D23: mois | E23: somme des probabilités de survie sur 12 mois
B24: MRR encaissé la première année (avec churn) | C24: ='Paramètres'!$C$7*'Unit economics'!$C$23 | D24: € | E24: prix_abonnement × mois_payés
B25: Euros de revenu par client la première année | C25: ='Paramètres'!$C$8+'Unit economics'!$C$22 | D25: € | E25: déploiement + 12 mois d'abonnement
B26: Euros/h facturés au client la première année | C26: ='Unit economics'!$C$25/'Unit economics'!$C$17 | D26: €/h | E26: revenu_client_an1 / heures_par_client
B27: Euros/h la première année, hors marketing | C27: ='Unit economics'!$C$25/('Hypothèses'!$C$16+'Unit economics'!$C$16) | D27: €/h | E27: revenu_client_an1 / (implémentation + prospection)
B28: Euros/h net IR la première année | C28: ='Unit economics'!$C$26*'Paramètres'!$C$37 | D28: €/h | E28: CA_horaire_an1 × taux_net_IR
B29: LTV brute (déploiement + abonnements) | C29: ='Paramètres'!$C$8+'Paramètres'!$C$7/'Hypothèses'!$C$33 | D29: € | E29: prix_déploiement + prix_abonnement / churn
B30: LTV nette d'impôt | C30: ='Unit economics'!$C$29*'Paramètres'!$C$37 | D30: € | E30: LTV_brute × taux_net_IR
B31: LTV nette par heure investie | C31: ='Unit economics'!$C$30/'Unit economics'!$C$17 | D31: €/h | E31: LTV_nette / heures_par_client
B32: Durée de vie moyenne d'un abonnement | C32: ='Hypothèses'!$C$35 | D32: mois | E32: 1 / churn_mensuel
B33: Churn mensuel équivalent | C33: ='Hypothèses'!$C$33 | D33: % | E33: 1 − rétention^(1/12)
B35: Comparatif : combien vaut une heure
B36: Salariat (heure de présence) | C36: ='Temps & capacité'!$C$16
B37: Salariat (heure de travail réel) | C37: ='Temps & capacité'!$C$17
B38: Implémentation facturée, net IR | C38: ='Unit economics'!$C$9
B39: Consultant première année, net IR | C39: ='Unit economics'!$C$28
B40: Au plateau, net IR | C40: ='Hypothèses'!$C$39/'Hypothèses'!$C$20

Sheet MRR mensuel
A1: Projection mensuelle du MRR
A2: 37 mois. Toutes les cellules sont des formules : modifiez la feuille Paramètres.
A3: Mois | B3: Nouveaux clients | C3: Clients perdus | D3: Clients actifs | E3: CA déploiement | F3: MRR | G3: CA total | H3: Net MRR | I3: Net déploiement | J3: Net consultant | K3: Salaire net IR | L3: Revenu total net | M3: Épargne | N3: CA cumulé | O3: Épargne cumulée | P3: Part MRR / CA | Q3: h / semaine | R3: j éq. / semaine
A4: =DATE('Paramètres'!$C$42,'Paramètres'!$C$43,1) | B4: ='Hypothèses'!$C$11 | C4: 0 | D4: =B4 | E4: =B4*'Paramètres'!$C$8 | F4: =D4*'Paramètres'!$C$7 | G4: =E4+F4 | H4: =F4*'Paramètres'!$C$37 | I4: =E4*'Paramètres'!$C$37 | J4: =G4*'Paramètres'!$C$37 | K4: ='Hypothèses'!$C$43 | L4: =J4+K4 | M4: =L4-'Paramètres'!$C$38 | N4: =G4 | O4: =M4 | P4: =IF(G4=0,0,F4/G4) | Q4: ='Hypothèses'!$C$22 | R4: ='Hypothèses'!$C$23
A5: =EDATE(A4,1) | B5: ='Hypothèses'!$C$11 | C5: =D4*'Hypothèses'!$C$33 | D5: =D4-C5+B5 | E5: =B5*'Paramètres'!$C$8 | F5: =D5*'Paramètres'!$C$7 | G5: =E5+F5 | H5: =F5*'Paramètres'!$C$37 | I5: =E5*'Paramètres'!$C$37 | J5: =G5*'Paramètres'!$C$37 | K5: ='Hypothèses'!$C$43 | L5: =J5+K5 | M5: =L5-'Paramètres'!$C$38 | N5: =N4+G5 | O5: =O4+M5 | P5: =IF(G5=0,0,F5/G5) | Q5: ='Hypothèses'!$C$22 | R5: ='Hypothèses'!$C$23
A6: =EDATE(A5,1) | B6: ='Hypothèses'!$C$11 | C6: =D5*'Hypothèses'!$C$33 | D6: =D5-C6+B6 | E6: =B6*'Paramètres'!$C$8 | F6: =D6*'Paramètres'!$C$7 | G6: =E6+F6 | H6: =F6*'Paramètres'!$C$37 | I6: =E6*'Paramètres'!$C$37 | J6: =G6*'Paramètres'!$C$37 | K6: ='Hypothèses'!$C$43 | L6: =J6+K6 | M6: =L6-'Paramètres'!$C$38 | N6: =N5+G6 | O6: =O5+M6 | P6: =IF(G6=0,0,F6/G6) | Q6: ='Hypothèses'!$C$22 | R6: ='Hypothèses'!$C$23
A7: =EDATE(A6,1) | B7: ='Hypothèses'!$C$11 | C7: =D6*'Hypothèses'!$C$33 | D7: =D6-C7+B7 | E7: =B7*'Paramètres'!$C$8 | F7: =D7*'Paramètres'!$C$7 | G7: =E7+F7 | H7: =F7*'Paramètres'!$C$37 | I7: =E7*'Paramètres'!$C$37 | J7: =G7*'Paramètres'!$C$37 | K7: ='Hypothèses'!$C$43 | L7: =J7+K7 | M7: =L7-'Paramètres'!$C$38 | N7: =N6+G7 | O7: =O6+M7 | P7: =IF(G7=0,0,F7/G7) | Q7: ='Hypothèses'!$C$22 | R7: ='Hypothèses'!$C$23
A8: =EDATE(A7,1) | B8: ='Hypothèses'!$C$11 | C8: =D7*'Hypothèses'!$C$33 | D8: =D7-C8+B8 | E8: =B8*'Paramètres'!$C$8 | F8: =D8*'Paramètres'!$C$7 | G8: =E8+F8 | H8: =F8*'Paramètres'!$C$37 | I8: =E8*'Paramètres'!$C$37 | J8: =G8*'Paramètres'!$C$37 | K8: ='Hypothèses'!$C$43 | L8: =J8+K8 | M8: =L8-'Paramètres'!$C$38 | N8: =N7+G8 | O8: =O7+M8 | P8: =IF(G8=0,0,F8/G8) | Q8: ='Hypothèses'!$C$22 | R8: ='Hypothèses'!$C$23
A9: =EDATE(A8,1) | B9: ='Hypothèses'!$C$11 | C9: =D8*'Hypothèses'!$C$33 | D9: =D8-C9+B9 | E9: =B9*'Paramètres'!$C$8 | F9: =D9*'Paramètres'!$C$7 | G9: =E9+F9 | H9: =F9*'Paramètres'!$C$37 | I9: =E9*'Paramètres'!$C$37 | J9: =G9*'Paramètres'!$C$37 | K9: ='Hypothèses'!$C$43 | L9: =J9+K9 | M9: =L9-'Paramètres'!$C$38 | N9: =N8+G9 | O9: =O8+M9 | P9: =IF(G9=0,0,F9/G9) | Q9: ='Hypothèses'!$C$22 | R9: ='Hypothèses'!$C$23
A10: =EDATE(A9,1) | B10: ='Hypothèses'!$C$11 | C10: =D9*'Hypothèses'!$C$33 | D10: =D9-C10+B10 | E10: =B10*'Paramètres'!$C$8 | F10: =D10*'Paramètres'!$C$7 | G10: =E10+F10 | H10: =F10*'Paramètres'!$C$37 | I10: =E10*'Paramètres'!$C$37 | J10: =G10*'Paramètres'!$C$37 | K10: ='Hypothèses'!$C$43 | L10: =J10+K10 | M10: =L10-'Paramètres'!$C$38 | N10: =N9+G10 | O10: =O9+M10 | P10: =IF(G10=0,0,F10/G10) | Q10: ='Hypothèses'!$C$22 | R10: ='Hypothèses'!$C$23
A11: =EDATE(A10,1) | B11: ='Hypothèses'!$C$11 | C11: =D10*'Hypothèses'!$C$33 | D11: =D10-C11+B11 | E11: =B11*'Paramètres'!$C$8 | F11: =D11*'Paramètres'!$C$7 | G11: =E11+F11 | H11: =F11*'Paramètres'!$C$37 | I11: =E11*'Paramètres'!$C$37 | J11: =G11*'Paramètres'!$C$37 | K11: ='Hypothèses'!$C$43 | L11: =J11+K11 | M11: =L11-'Paramètres'!$C$38 | N11: =N10+G11 | O11: =O10+M11 | P11: =IF(G11=0,0,F11/G11) | Q11: ='Hypothèses'!$C$22 | R11: ='Hypothèses'!$C$23
A12: =EDATE(A11,1) | B12: ='Hypothèses'!$C$11 | C12: =D11*'Hypothèses'!$C$33 | D12: =D11-C12+B12 | E12: =B12*'Paramètres'!$C$8 | F12: =D12*'Paramètres'!$C$7 | G12: =E12+F12 | H12: =F12*'Paramètres'!$C$37 | I12: =E12*'Paramètres'!$C$37 | J12: =G12*'Paramètres'!$C$37 | K12: ='Hypothèses'!$C$43 | L12: =J12+K12 | M12: =L12-'Paramètres'!$C$38 | N12: =N11+G12 | O12: =O11+M12 | P12: =IF(G12=0,0,F12/G12) | Q12: ='Hypothèses'!$C$22 | R12: ='Hypothèses'!$C$23
A13: =EDATE(A12,1) | B13: ='Hypothèses'!$C$11 | C13: =D12*'Hypothèses'!$C$33 | D13: =D12-C13+B13 | E13: =B13*'Paramètres'!$C$8 | F13: =D13*'Paramètres'!$C$7 | G13: =E13+F13 | H13: =F13*'Paramètres'!$C$37 | I13: =E13*'Paramètres'!$C$37 | J13: =G13*'Paramètres'!$C$37 | K13: ='Hypothèses'!$C$43 | L13: =J13+K13 | M13: =L13-'Paramètres'!$C$38 | N13: =N12+G13 | O13: =O12+M13 | P13: =IF(G13=0,0,F13/G13) | Q13: ='Hypothèses'!$C$22 | R13: ='Hypothèses'!$C$23
A14: =EDATE(A13,1) | B14: ='Hypothèses'!$C$11 | C14: =D13*'Hypothèses'!$C$33 | D14: =D13-C14+B14 | E14: =B14*'Paramètres'!$C$8 | F14: =D14*'Paramètres'!$C$7 | G14: =E14+F14 | H14: =F14*'Paramètres'!$C$37 | I14: =E14*'Paramètres'!$C$37 | J14: =G14*'Paramètres'!$C$37 | K14: ='Hypothèses'!$C$43 | L14: =J14+K14 | M14: =L14-'Paramètres'!$C$38 | N14: =N13+G14 | O14: =O13+M14 | P14: =IF(G14=0,0,F14/G14) | Q14: ='Hypothèses'!$C$22 | R14: ='Hypothèses'!$C$23
A15: =EDATE(A14,1) | B15: ='Hypothèses'!$C$11 | C15: =D14*'Hypothèses'!$C$33 | D15: =D14-C15+B15 | E15: =B15*'Paramètres'!$C$8 | F15: =D15*'Paramètres'!$C$7 | G15: =E15+F15 | H15: =F15*'Paramètres'!$C$37 | I15: =E15*'Paramètres'!$C$37 | J15: =G15*'Paramètres'!$C$37 | K15: ='Hypothèses'!$C$43 | L15: =J15+K15 | M15: =L15-'Paramètres'!$C$38 | N15: =N14+G15 | O15: =O14+M15 | P15: =IF(G15=0,0,F15/G15) | Q15: ='Hypothèses'!$C$22 | R15: ='Hypothèses'!$C$23
A16: =EDATE(A15,1) | B16: ='Hypothèses'!$C$11 | C16: =D15*'Hypothèses'!$C$33 | D16: =D15-C16+B16 | E16: =B16*'Paramètres'!$C$8 | F16: =D16*'Paramètres'!$C$7 | G16: =E16+F16 | H16: =F16*'Paramètres'!$C$37 | I16: =E16*'Paramètres'!$C$37 | J16: =G16*'Paramètres'!$C$37 | K16: ='Hypothèses'!$C$43 | L16: =J16+K16 | M16: =L16-'Paramètres'!$C$38 | N16: =N15+G16 | O16: =O15+M16 | P16: =IF(G16=0,0,F16/G16) | Q16: ='Hypothèses'!$C$22 | R16: ='Hypothèses'!$C$23
... A40: =EDATE(A39,1) | B40: ='Hypothèses'!$C$11 | C40: =D39*'Hypothèses'!$C$33 | D40: =D39-C40+B40 | E40: =B40*'Paramètres'!$C$8 | F40: =D40*'Paramètres'!$C$7 | G40: =E40+F40 | H40: =F40*'Paramètres'!$C$37 | I40: =E40*'Paramètres'!$C$37 | J40: =G40*'Paramètres'!$C$37 | K40: ='Hypothèses'!$C$43 | L40: =J40+K40 | M40: =L40-'Paramètres'!$C$38 | N40: =N39+G40 | O40: =O39+M40 | P40: =IF(G40=0,0,F40/G40) | Q40: ='Hypothèses'!$C$22 | R40: ='Hypothèses'!$C$23
A41: Total 37 mois | B41: =SUM(B4:B40) | C41: =SUM(C4:C40) | D41: =D40 | E41: =SUM(E4:E40) | F41: =SUM(F4:F40) | G41: =SUM(G4:G40) | H41: =SUM(H4:H40) | I41: =SUM(I4:I40) | J41: =SUM(J4:J40) | K41: =SUM(K4:K40) | L41: =SUM(L4:L40) | M41: =SUM(M4:M40)

Sheet Synthèse annuelle
A1: Synthèse par exercice
A2: Agrégats calculés par année civile sur la feuille MRR mensuel.
A4: Exercice | B4: Mois | C4: CA déploiement | D4: CA abonnements | E4: CA total | F4: Part MRR | G4: Net consultant | H4: Salaire net IR | I4: Revenu total net | J4: Dépenses | K4: Épargne | L4: Clients fin | M4: MRR fin | N4: Heures | O4: €/h net | P4: €/jour
A5: ='Paramètres'!$C$42 | B5: =SUMPRODUCT(--(YEAR('MRR mensuel'!$A$4:$A$40)=$A5)) | C5: =SUMPRODUCT((YEAR('MRR mensuel'!$A$4:$A$40)=$A5)*'MRR mensuel'!$E$4:$E$40) | D5: =SUMPRODUCT((YEAR('MRR mensuel'!$A$4:$A$40)=$A5)*'MRR mensuel'!$F$4:$F$40) | E5: =C5+D5 | F5: =IF(E5=0,0,D5/E5) | G5: =SUMPRODUCT((YEAR('MRR mensuel'!$A$4:$A$40)=$A5)*'MRR mensuel'!$J$4:$J$40) | H5: =SUMPRODUCT((YEAR('MRR mensuel'!$A$4:$A$40)=$A5)*'MRR mensuel'!$K$4:$K$40) | I5: =G5+H5 | J5: =B5*'Paramètres'!$C$38 | K5: =I5-J5 | L5: =IFERROR(LOOKUP(2,1/(YEAR('MRR mensuel'!$A$4:$A$40)=$A5),'MRR mensuel'!$D$4:$D$40),0) | M5: =IFERROR(LOOKUP(2,1/(YEAR('MRR mensuel'!$A$4:$A$40)=$A5),'MRR mensuel'!$F$4:$F$40),0) | N5: ='Hypothèses'!$C$20*B5/12 | O5: =IF(N5=0,0,G5/N5) | P5: =IF(B5=0,0,I5/('Paramètres'!$C$21*B5/12))
A6: ='Paramètres'!$C$42+1 | B6: =SUMPRODUCT(--(YEAR('MRR mensuel'!$A$4:$A$40)=$A6)) | C6: =SUMPRODUCT((YEAR('MRR mensuel'!$A$4:$A$40)=$A6)*'MRR mensuel'!$E$4:$E$40) | D6: =SUMPRODUCT((YEAR('MRR mensuel'!$A$4:$A$40)=$A6)*'MRR mensuel'!$F$4:$F$40) | E6: =C6+D6 | F6: =IF(E6=0,0,D6/E6) | G6: =SUMPRODUCT((YEAR('MRR mensuel'!$A$4:$A$40)=$A6)*'MRR mensuel'!$J$4:$J$40) | H6: =SUMPRODUCT((YEAR('MRR mensuel'!$A$4:$A$40)=$A6)*'MRR mensuel'!$K$4:$K$40) | I6: =G6+H6 | J6: =B6*'Paramètres'!$C$38 | K6: =I6-J6 | L6: =IFERROR(LOOKUP(2,1/(YEAR('MRR mensuel'!$A$4:$A$40)=$A6),'MRR mensuel'!$D$4:$D$40),0) | M6: =IFERROR(LOOKUP(2,1/(YEAR('MRR mensuel'!$A$4:$A$40)=$A6),'MRR mensuel'!$F$4:$F$40),0) | N6: ='Hypothèses'!$C$20*B6/12 | O6: =IF(N6=0,0,G6/N6) | P6: =IF(B6=0,0,I6/('Paramètres'!$C$21*B6/12))
A7: ='Paramètres'!$C$42+2 | B7: =SUMPRODUCT(--(YEAR('MRR mensuel'!$A$4:$A$40)=$A7)) | C7: =SUMPRODUCT((YEAR('MRR mensuel'!$A$4:$A$40)=$A7)*'MRR mensuel'!$E$4:$E$40) | D7: =SUMPRODUCT((YEAR('MRR mensuel'!$A$4:$A$40)=$A7)*'MRR mensuel'!$F$4:$F$40) | E7: =C7+D7 | F7: =IF(E7=0,0,D7/E7) | G7: =SUMPRODUCT((YEAR('MRR mensuel'!$A$4:$A$40)=$A7)*'MRR mensuel'!$J$4:$J$40) | H7: =SUMPRODUCT((YEAR('MRR mensuel'!$A$4:$A$40)=$A7)*'MRR mensuel'!$K$4:$K$40) | I7: =G7+H7 | J7: =B7*'Paramètres'!$C$38 | K7: =I7-J7 | L7: =IFERROR(LOOKUP(2,1/(YEAR('MRR mensuel'!$A$4:$A$40)=$A7),'MRR mensuel'!$D$4:$D$40),0) | M7: =IFERROR(LOOKUP(2,1/(YEAR('MRR mensuel'!$A$4:$A$40)=$A7),'MRR mensuel'!$F$4:$F$40),0) | N7: ='Hypothèses'!$C$20*B7/12 | O7: =IF(N7=0,0,G7/N7) | P7: =IF(B7=0,0,I7/('Paramètres'!$C$21*B7/12))
A8: ='Paramètres'!$C$42+3 | B8: =SUMPRODUCT(--(YEAR('MRR mensuel'!$A$4:$A$40)=$A8)) | C8: =SUMPRODUCT((YEAR('MRR mensuel'!$A$4:$A$40)=$A8)*'MRR mensuel'!$E$4:$E$40) | D8: =SUMPRODUCT((YEAR('MRR mensuel'!$A$4:$A$40)=$A8)*'MRR mensuel'!$F$4:$F$40) | E8: =C8+D8 | F8: =IF(E8=0,0,D8/E8) | G8: =SUMPRODUCT((YEAR('MRR mensuel'!$A$4:$A$40)=$A8)*'MRR mensuel'!$J$4:$J$40) | H8: =SUMPRODUCT((YEAR('MRR mensuel'!$A$4:$A$40)=$A8)*'MRR mensuel'!$K$4:$K$40) | I8: =G8+H8 | J8: =B8*'Paramètres'!$C$38 | K8: =I8-J8 | L8: =IFERROR(LOOKUP(2,1/(YEAR('MRR mensuel'!$A$4:$A$40)=$A8),'MRR mensuel'!$D$4:$D$40),0) | M8: =IFERROR(LOOKUP(2,1/(YEAR('MRR mensuel'!$A$4:$A$40)=$A8),'MRR mensuel'!$F$4:$F$40),0) | N8: ='Hypothèses'!$C$20*B8/12 | O8: =IF(N8=0,0,G8/N8) | P8: =IF(B8=0,0,I8/('Paramètres'!$C$21*B8/12))
A9: Total | B9: =SUM(B5:B8) | C9: =SUM(C5:C8) | D9: =SUM(D5:D8) | E9: =SUM(E5:E8) | F9: =IF(E9=0,0,D9/E9) | G9: =SUM(G5:G8) | H9: =SUM(H5:H8) | I9: =SUM(I5:I8) | J9: =SUM(J5:J8) | K9: =SUM(K5:K8) | N9: =SUM(N5:N8)

Sheet Jalons
B2: Jalons et seuils
B3: Date de franchissement de chaque seuil, cherchée dans la feuille MRR mensuel.
B5: Jalon | C5: Condition | D5: Date | E5: Rang | F5: MRR à cette date
B6: Le MRR dépasse le CA de déploiement | C6: MRR ≥ CA déploiement | D6: =IFERROR(INDEX('MRR mensuel'!$A$4:$A$40,MATCH(TRUE,('MRR mensuel'!$F$4:$F$40>='MRR mensuel'!$E$4:$E$40),0)),"hors horizon") | E6: =IFERROR("M+"&MATCH(TRUE,('MRR mensuel'!$F$4:$F$40>='MRR mensuel'!$E$4:$E$40),0),"—") | F6: =IFERROR(INDEX('MRR mensuel'!$F$4:$F$40,MATCH(TRUE,('MRR mensuel'!$F$4:$F$40>='MRR mensuel'!$E$4:$E$40),0)),"—")
B7: Le net consultant couvre les dépenses | C7: net consultant ≥ dépenses | D7: =IFERROR(INDEX('MRR mensuel'!$A$4:$A$40,MATCH(TRUE,('MRR mensuel'!$J$4:$J$40>='Paramètres'!$C$38),0)),"hors horizon") | E7: =IFERROR("M+"&MATCH(TRUE,('MRR mensuel'!$J$4:$J$40>='Paramètres'!$C$38),0),"—") | F7: =IFERROR(INDEX('MRR mensuel'!$F$4:$F$40,MATCH(TRUE,('MRR mensuel'!$J$4:$J$40>='Paramètres'!$C$38),0)),"—")
B8: MRR à 1 000 €/mois | C8: MRR ≥ 1 000 € | D8: =IFERROR(INDEX('MRR mensuel'!$A$4:$A$40,MATCH(TRUE,('MRR mensuel'!$F$4:$F$40>=1000),0)),"hors horizon") | E8: =IFERROR("M+"&MATCH(TRUE,('MRR mensuel'!$F$4:$F$40>=1000),0),"—") | F8: =IFERROR(INDEX('MRR mensuel'!$F$4:$F$40,MATCH(TRUE,('MRR mensuel'!$F$4:$F$40>=1000),0)),"—")
B9: Le net consultant égale le salaire net IR | C9: net consultant ≥ salaire net | D9: =IFERROR(INDEX('MRR mensuel'!$A$4:$A$40,MATCH(TRUE,('MRR mensuel'!$J$4:$J$40>='Hypothèses'!$C$43),0)),"hors horizon") | E9: =IFERROR("M+"&MATCH(TRUE,('MRR mensuel'!$J$4:$J$40>='Hypothèses'!$C$43),0),"—") | F9: =IFERROR(INDEX('MRR mensuel'!$F$4:$F$40,MATCH(TRUE,('MRR mensuel'!$J$4:$J$40>='Hypothèses'!$C$43),0)),"—")
B10: MRR à 5 000 €/mois | C10: MRR ≥ 5 000 € | D10: =IFERROR(INDEX('MRR mensuel'!$A$4:$A$40,MATCH(TRUE,('MRR mensuel'!$F$4:$F$40>=5000),0)),"hors horizon") | E10: =IFERROR("M+"&MATCH(TRUE,('MRR mensuel'!$F$4:$F$40>=5000),0),"—") | F10: =IFERROR(INDEX('MRR mensuel'!$F$4:$F$40,MATCH(TRUE,('MRR mensuel'!$F$4:$F$40>=5000),0)),"—")
B11: Le MRR net seul couvre les dépenses | C11: net MRR ≥ dépenses | D11: =IFERROR(INDEX('MRR mensuel'!$A$4:$A$40,MATCH(TRUE,('MRR mensuel'!$H$4:$H$40>='Paramètres'!$C$38),0)),"hors horizon") | E11: =IFERROR("M+"&MATCH(TRUE,('MRR mensuel'!$H$4:$H$40>='Paramètres'!$C$38),0),"—") | F11: =IFERROR(INDEX('MRR mensuel'!$F$4:$F$40,MATCH(TRUE,('MRR mensuel'!$H$4:$H$40>='Paramètres'!$C$38),0)),"—")
B12: Le revenu total double le salaire net | C12: revenu total ≥ 2 × salaire net | D12: =IFERROR(INDEX('MRR mensuel'!$A$4:$A$40,MATCH(TRUE,('MRR mensuel'!$L$4:$L$40>=2*'Hypothèses'!$C$43),0)),"hors horizon") | E12: =IFERROR("M+"&MATCH(TRUE,('MRR mensuel'!$L$4:$L$40>=2*'Hypothèses'!$C$43),0),"—") | F12: =IFERROR(INDEX('MRR mensuel'!$F$4:$F$40,MATCH(TRUE,('MRR mensuel'!$L$4:$L$40>=2*'Hypothèses'!$C$43),0)),"—")
B13: MRR à 10 000 €/mois | C13: MRR ≥ 10 000 € | D13: =IFERROR(INDEX('MRR mensuel'!$A$4:$A$40,MATCH(TRUE,('MRR mensuel'!$F$4:$F$40>=10000),0)),"hors horizon") | E13: =IFERROR("M+"&MATCH(TRUE,('MRR mensuel'!$F$4:$F$40>=10000),0),"—") | F13: =IFERROR(INDEX('MRR mensuel'!$F$4:$F$40,MATCH(TRUE,('MRR mensuel'!$F$4:$F$40>=10000),0)),"—")
B15: Les formules MATCH(TRUE;…;0) sont matricielles. Google Sheets les évalue directement ;
B16: dans Excel, valider par Ctrl+Maj+Entrée si une version antérieure à 2021 est utilisée.

Sheet Sensibilité
B2: Analyse de sensibilité
B3: MRR atteint au 37ᵉ mois selon deux couples d'hypothèses.
B5: Levier volume — diagnostics/semaine × taux de conversion
B6: Diag. \ Conversion | C6: 0.2 | D6: 0.3 | E6: 0.4 | F6: 0.5 | G6: 0.6 | H6: 0.75
B7: 0.5 | C7: =(($B7*('Paramètres'!$C$21/5)*C$6)/12)*(1-(1-(1-'Paramètres'!$C$17^(1/12)))^37)/(1-'Paramètres'!$C$17^(1/12))*'Paramètres'!$C$7 | D7: =(($B7*('Paramètres'!$C$21/5)*D$6)/12)*(1-(1-(1-'Paramètres'!$C$17^(1/12)))^37)/(1-'Paramètres'!$C$17^(1/12))*'Paramètres'!$C$7 | E7: =(($B7*('Paramètres'!$C$21/5)*E$6)/12)*(1-(1-(1-'Paramètres'!$C$17^(1/12)))^37)/(1-'Paramètres'!$C$17^(1/12))*'Paramètres'!$C$7 | F7: =(($B7*('Paramètres'!$C$21/5)*F$6)/12)*(1-(1-(1-'Paramètres'!$C$17^(1/12)))^37)/(1-'Paramètres'!$C$17^(1/12))*'Paramètres'!$C$7 | G7: =(($B7*('Paramètres'!$C$21/5)*G$6)/12)*(1-(1-(1-'Paramètres'!$C$17^(1/12)))^37)/(1-'Paramètres'!$C$17^(1/12))*'Paramètres'!$C$7 | H7: =(($B7*('Paramètres'!$C$21/5)*H$6)/12)*(1-(1-(1-'Paramètres'!$C$17^(1/12)))^37)/(1-'Paramètres'!$C$17^(1/12))*'Paramètres'!$C$7
B8: 0.75 | C8: =(($B8*('Paramètres'!$C$21/5)*C$6)/12)*(1-(1-(1-'Paramètres'!$C$17^(1/12)))^37)/(1-'Paramètres'!$C$17^(1/12))*'Paramètres'!$C$7 | D8: =(($B8*('Paramètres'!$C$21/5)*D$6)/12)*(1-(1-(1-'Paramètres'!$C$17^(1/12)))^37)/(1-'Paramètres'!$C$17^(1/12))*'Paramètres'!$C$7 | E8: =(($B8*('Paramètres'!$C$21/5)*E$6)/12)*(1-(1-(1-'Paramètres'!$C$17^(1/12)))^37)/(1-'Paramètres'!$C$17^(1/12))*'Paramètres'!$C$7 | F8: =(($B8*('Paramètres'!$C$21/5)*F$6)/12)*(1-(1-(1-'Paramètres'!$C$17^(1/12)))^37)/(1-'Paramètres'!$C$17^(1/12))*'Paramètres'!$C$7 | G8: =(($B8*('Paramètres'!$C$21/5)*G$6)/12)*(1-(1-(1-'Paramètres'!$C$17^(1/12)))^37)/(1-'Paramètres'!$C$17^(1/12))*'Paramètres'!$C$7 | H8: =(($B8*('Paramètres'!$C$21/5)*H$6)/12)*(1-(1-(1-'Paramètres'!$C$17^(1/12)))^37)/(1-'Paramètres'!$C$17^(1/12))*'Paramètres'!$C$7
B9: 1 | C9: =(($B9*('Paramètres'!$C$21/5)*C$6)/12)*(1-(1-(1-'Paramètres'!$C$17^(1/12)))^37)/(1-'Paramètres'!$C$17^(1/12))*'Paramètres'!$C$7 | D9: =(($B9*('Paramètres'!$C$21/5)*D$6)/12)*(1-(1-(1-'Paramètres'!$C$17^(1/12)))^37)/(1-'Paramètres'!$C$17^(1/12))*'Paramètres'!$C$7 | E9: =(($B9*('Paramètres'!$C$21/5)*E$6)/12)*(1-(1-(1-'Paramètres'!$C$17^(1/12)))^37)/(1-'Paramètres'!$C$17^(1/12))*'Paramètres'!$C$7 | F9: =(($B9*('Paramètres'!$C$21/5)*F$6)/12)*(1-(1-(1-'Paramètres'!$C$17^(1/12)))^37)/(1-'Paramètres'!$C$17^(1/12))*'Paramètres'!$C$7 | G9: =(($B9*('Paramètres'!$C$21/5)*G$6)/12)*(1-(1-(1-'Paramètres'!$C$17^(1/12)))^37)/(1-'Paramètres'!$C$17^(1/12))*'Paramètres'!$C$7 | H9: =(($B9*('Paramètres'!$C$21/5)*H$6)/12)*(1-(1-(1-'Paramètres'!$C$17^(1/12)))^37)/(1-'Paramètres'!$C$17^(1/12))*'Paramètres'!$C$7
B10: 1.5 | C10: =(($B10*('Paramètres'!$C$21/5)*C$6)/12)*(1-(1-(1-'Paramètres'!$C$17^(1/12)))^37)/(1-'Paramètres'!$C$17^(1/12))*'Paramètres'!$C$7 | D10: =(($B10*('Paramètres'!$C$21/5)*D$6)/12)*(1-(1-(1-'Paramètres'!$C$17^(1/12)))^37)/(1-'Paramètres'!$C$17^(1/12))*'Paramètres'!$C$7 | E10: =(($B10*('Paramètres'!$C$21/5)*E$6)/12)*(1-(1-(1-'Paramètres'!$C$17^(1/12)))^37)/(1-'Paramètres'!$C$17^(1/12))*'Paramètres'!$C$7 | F10: =(($B10*('Paramètres'!$C$21/5)*F$6)/12)*(1-(1-(1-'Paramètres'!$C$17^(1/12)))^37)/(1-'Paramètres'!$C$17^(1/12))*'Paramètres'!$C$7 | G10: =(($B10*('Paramètres'!$C$21/5)*G$6)/12)*(1-(1-(1-'Paramètres'!$C$17^(1/12)))^37)/(1-'Paramètres'!$C$17^(1/12))*'Paramètres'!$C$7 | H10: =(($B10*('Paramètres'!$C$21/5)*H$6)/12)*(1-(1-(1-'Paramètres'!$C$17^(1/12)))^37)/(1-'Paramètres'!$C$17^(1/12))*'Paramètres'!$C$7
B11: 2 | C11: =(($B11*('Paramètres'!$C$21/5)*C$6)/12)*(1-(1-(1-'Paramètres'!$C$17^(1/12)))^37)/(1-'Paramètres'!$C$17^(1/12))*'Paramètres'!$C$7 | D11: =(($B11*('Paramètres'!$C$21/5)*D$6)/12)*(1-(1-(1-'Paramètres'!$C$17^(1/12)))^37)/(1-'Paramètres'!$C$17^(1/12))*'Paramètres'!$C$7 | E11: =(($B11*('Paramètres'!$C$21/5)*E$6)/12)*(1-(1-(1-'Paramètres'!$C$17^(1/12)))^37)/(1-'Paramètres'!$C$17^(1/12))*'Paramètres'!$C$7 | F11: =(($B11*('Paramètres'!$C$21/5)*F$6)/12)*(1-(1-(1-'Paramètres'!$C$17^(1/12)))^37)/(1-'Paramètres'!$C$17^(1/12))*'Paramètres'!$C$7 | G11: =(($B11*('Paramètres'!$C$21/5)*G$6)/12)*(1-(1-(1-'Paramètres'!$C$17^(1/12)))^37)/(1-'Paramètres'!$C$17^(1/12))*'Paramètres'!$C$7 | H11: =(($B11*('Paramètres'!$C$21/5)*H$6)/12)*(1-(1-(1-'Paramètres'!$C$17^(1/12)))^37)/(1-'Paramètres'!$C$17^(1/12))*'Paramètres'!$C$7
B12: 3 | C12: =(($B12*('Paramètres'!$C$21/5)*C$6)/12)*(1-(1-(1-'Paramètres'!$C$17^(1/12)))^37)/(1-'Paramètres'!$C$17^(1/12))*'Paramètres'!$C$7 | D12: =(($B12*('Paramètres'!$C$21/5)*D$6)/12)*(1-(1-(1-'Paramètres'!$C$17^(1/12)))^37)/(1-'Paramètres'!$C$17^(1/12))*'Paramètres'!$C$7 | E12: =(($B12*('Paramètres'!$C$21/5)*E$6)/12)*(1-(1-(1-'Paramètres'!$C$17^(1/12)))^37)/(1-'Paramètres'!$C$17^(1/12))*'Paramètres'!$C$7 | F12: =(($B12*('Paramètres'!$C$21/5)*F$6)/12)*(1-(1-(1-'Paramètres'!$C$17^(1/12)))^37)/(1-'Paramètres'!$C$17^(1/12))*'Paramètres'!$C$7 | G12: =(($B12*('Paramètres'!$C$21/5)*G$6)/12)*(1-(1-(1-'Paramètres'!$C$17^(1/12)))^37)/(1-'Paramètres'!$C$17^(1/12))*'Paramètres'!$C$7 | H12: =(($B12*('Paramètres'!$C$21/5)*H$6)/12)*(1-(1-(1-'Paramètres'!$C$17^(1/12)))^37)/(1-'Paramètres'!$C$17^(1/12))*'Paramètres'!$C$7
B15: Levier valeur — prix de l'abonnement × taux de rétention
B16: Prix \ Rétention | C16: 0.6 | D16: 0.7 | E16: 0.8 | F16: 0.85 | G16: 0.92 | H16: 0.97
B17: 95 | C17: =(('Paramètres'!$C$13*('Paramètres'!$C$21/5)*'Paramètres'!$C$15)/12)*(1-(1-(1-C$16^(1/12)))^37)/(1-C$16^(1/12))*$B17 | D17: =(('Paramètres'!$C$13*('Paramètres'!$C$21/5)*'Paramètres'!$C$15)/12)*(1-(1-(1-D$16^(1/12)))^37)/(1-D$16^(1/12))*$B17 | E17: =(('Paramètres'!$C$13*('Paramètres'!$C$21/5)*'Paramètres'!$C$15)/12)*(1-(1-(1-E$16^(1/12)))^37)/(1-E$16^(1/12))*$B17 | F17: =(('Paramètres'!$C$13*('Paramètres'!$C$21/5)*'Paramètres'!$C$15)/12)*(1-(1-(1-F$16^(1/12)))^37)/(1-F$16^(1/12))*$B17 | G17: =(('Paramètres'!$C$13*('Paramètres'!$C$21/5)*'Paramètres'!$C$15)/12)*(1-(1-(1-G$16^(1/12)))^37)/(1-G$16^(1/12))*$B17 | H17: =(('Paramètres'!$C$13*('Paramètres'!$C$21/5)*'Paramètres'!$C$15)/12)*(1-(1-(1-H$16^(1/12)))^37)/(1-H$16^(1/12))*$B17
B18: 145 | C18: =(('Paramètres'!$C$13*('Paramètres'!$C$21/5)*'Paramètres'!$C$15)/12)*(1-(1-(1-C$16^(1/12)))^37)/(1-C$16^(1/12))*$B18 | D18: =(('Paramètres'!$C$13*('Paramètres'!$C$21/5)*'Paramètres'!$C$15)/12)*(1-(1-(1-D$16^(1/12)))^37)/(1-D$16^(1/12))*$B18 | E18: =(('Paramètres'!$C$13*('Paramètres'!$C$21/5)*'Paramètres'!$C$15)/12)*(1-(1-(1-E$16^(1/12)))^37)/(1-E$16^(1/12))*$B18 | F18: =(('Paramètres'!$C$13*('Paramètres'!$C$21/5)*'Paramètres'!$C$15)/12)*(1-(1-(1-F$16^(1/12)))^37)/(1-F$16^(1/12))*$B18 | G18: =(('Paramètres'!$C$13*('Paramètres'!$C$21/5)*'Paramètres'!$C$15)/12)*(1-(1-(1-G$16^(1/12)))^37)/(1-G$16^(1/12))*$B18 | H18: =(('Paramètres'!$C$13*('Paramètres'!$C$21/5)*'Paramètres'!$C$15)/12)*(1-(1-(1-H$16^(1/12)))^37)/(1-H$16^(1/12))*$B18
B19: 185 | C19: =(('Paramètres'!$C$13*('Paramètres'!$C$21/5)*'Paramètres'!$C$15)/12)*(1-(1-(1-C$16^(1/12)))^37)/(1-C$16^(1/12))*$B19 | D19: =(('Paramètres'!$C$13*('Paramètres'!$C$21/5)*'Paramètres'!$C$15)/12)*(1-(1-(1-D$16^(1/12)))^37)/(1-D$16^(1/12))*$B19 | E19: =(('Paramètres'!$C$13*('Paramètres'!$C$21/5)*'Paramètres'!$C$15)/12)*(1-(1-(1-E$16^(1/12)))^37)/(1-E$16^(1/12))*$B19 | F19: =(('Paramètres'!$C$13*('Paramètres'!$C$21/5)*'Paramètres'!$C$15)/12)*(1-(1-(1-F$16^(1/12)))^37)/(1-F$16^(1/12))*$B19 | G19: =(('Paramètres'!$C$13*('Paramètres'!$C$21/5)*'Paramètres'!$C$15)/12)*(1-(1-(1-G$16^(1/12)))^37)/(1-G$16^(1/12))*$B19 | H19: =(('Paramètres'!$C$13*('Paramètres'!$C$21/5)*'Paramètres'!$C$15)/12)*(1-(1-(1-H$16^(1/12)))^37)/(1-H$16^(1/12))*$B19
B20: 245 | C20: =(('Paramètres'!$C$13*('Paramètres'!$C$21/5)*'Paramètres'!$C$15)/12)*(1-(1-(1-C$16^(1/12)))^37)/(1-C$16^(1/12))*$B20 | D20: =(('Paramètres'!$C$13*('Paramètres'!$C$21/5)*'Paramètres'!$C$15)/12)*(1-(1-(1-D$16^(1/12)))^37)/(1-D$16^(1/12))*$B20 | E20: =(('Paramètres'!$C$13*('Paramètres'!$C$21/5)*'Paramètres'!$C$15)/12)*(1-(1-(1-E$16^(1/12)))^37)/(1-E$16^(1/12))*$B20 | F20: =(('Paramètres'!$C$13*('Paramètres'!$C$21/5)*'Paramètres'!$C$15)/12)*(1-(1-(1-F$16^(1/12)))^37)/(1-F$16^(1/12))*$B20 | G20: =(('Paramètres'!$C$13*('Paramètres'!$C$21/5)*'Paramètres'!$C$15)/12)*(1-(1-(1-G$16^(1/12)))^37)/(1-G$16^(1/12))*$B20 | H20: =(('Paramètres'!$C$13*('Paramètres'!$C$21/5)*'Paramètres'!$C$15)/12)*(1-(1-(1-H$16^(1/12)))^37)/(1-H$16^(1/12))*$B20
B21: 320 | C21: =(('Paramètres'!$C$13*('Paramètres'!$C$21/5)*'Paramètres'!$C$15)/12)*(1-(1-(1-C$16^(1/12)))^37)/(1-C$16^(1/12))*$B21 | D21: =(('Paramètres'!$C$13*('Paramètres'!$C$21/5)*'Paramètres'!$C$15)/12)*(1-(1-(1-D$16^(1/12)))^37)/(1-D$16^(1/12))*$B21 | E21: =(('Paramètres'!$C$13*('Paramètres'!$C$21/5)*'Paramètres'!$C$15)/12)*(1-(1-(1-E$16^(1/12)))^37)/(1-E$16^(1/12))*$B21 | F21: =(('Paramètres'!$C$13*('Paramètres'!$C$21/5)*'Paramètres'!$C$15)/12)*(1-(1-(1-F$16^(1/12)))^37)/(1-F$16^(1/12))*$B21 | G21: =(('Paramètres'!$C$13*('Paramètres'!$C$21/5)*'Paramètres'!$C$15)/12)*(1-(1-(1-G$16^(1/12)))^37)/(1-G$16^(1/12))*$B21 | H21: =(('Paramètres'!$C$13*('Paramètres'!$C$21/5)*'Paramètres'!$C$15)/12)*(1-(1-(1-H$16^(1/12)))^37)/(1-H$16^(1/12))*$B21
B22: 450 | C22: =(('Paramètres'!$C$13*('Paramètres'!$C$21/5)*'Paramètres'!$C$15)/12)*(1-(1-(1-C$16^(1/12)))^37)/(1-C$16^(1/12))*$B22 | D22: =(('Paramètres'!$C$13*('Paramètres'!$C$21/5)*'Paramètres'!$C$15)/12)*(1-(1-(1-D$16^(1/12)))^37)/(1-D$16^(1/12))*$B22 | E22: =(('Paramètres'!$C$13*('Paramètres'!$C$21/5)*'Paramètres'!$C$15)/12)*(1-(1-(1-E$16^(1/12)))^37)/(1-E$16^(1/12))*$B22 | F22: =(('Paramètres'!$C$13*('Paramètres'!$C$21/5)*'Paramètres'!$C$15)/12)*(1-(1-(1-F$16^(1/12)))^37)/(1-F$16^(1/12))*$B22 | G22: =(('Paramètres'!$C$13*('Paramètres'!$C$21/5)*'Paramètres'!$C$15)/12)*(1-(1-(1-G$16^(1/12)))^37)/(1-G$16^(1/12))*$B22 | H22: =(('Paramètres'!$C$13*('Paramètres'!$C$21/5)*'Paramètres'!$C$15)/12)*(1-(1-(1-H$16^(1/12)))^37)/(1-H$16^(1/12))*$B22
B25: Lecture : chaque cellule recalcule le MRR du 37ᵉ mois en ne changeant que les deux
B26: variables de la matrice. Les autres paramètres restent ceux de la feuille Paramètres.

Sheet Scénarios
B2: Scénarios
B3: Cinq trajectoires. Les hypothèses de chaque ligne sont modifiables directement ici.
B5: Scénario | C5: Diagnostics/sem | D5: Conversion | E5: Rétention | F5: Prix abo | G5: Clients au 37ᵉ mois | H5: MRR au 37ᵉ mois | I5: Net moyen/mois
B6: Pessimiste | C6: 1 | D6: 0.25 | E6: 0.65 | F6: 148 | G6: =(($C6*('Paramètres'!$C$21/5)*$D6)/12)*(1-(1-(1-$E6^(1/12)))^37)/(1-$E6^(1/12)) | H6: =G6*$F6 | I6: =(((($C6*('Paramètres'!$C$21/5)*$D6)/12)/(1-$E6^(1/12)))*(1-(1-(1-(1-$E6^(1/12)))^37)/(37*(1-$E6^(1/12))))*$F6+(($C6*('Paramètres'!$C$21/5)*$D6)/12)*'Paramètres'!$C$8)*'Paramètres'!$C$37
B7: Prudent | C7: 1 | D7: 0.375 | E7: 0.75 | F7: 185 | G7: =(($C7*('Paramètres'!$C$21/5)*$D7)/12)*(1-(1-(1-$E7^(1/12)))^37)/(1-$E7^(1/12)) | H7: =G7*$F7 | I7: =(((($C7*('Paramètres'!$C$21/5)*$D7)/12)/(1-$E7^(1/12)))*(1-(1-(1-(1-$E7^(1/12)))^37)/(37*(1-$E7^(1/12))))*$F7+(($C7*('Paramètres'!$C$21/5)*$D7)/12)*'Paramètres'!$C$8)*'Paramètres'!$C$37
B8: Référence | C8: ='Paramètres'!$C$13 | D8: ='Paramètres'!$C$15 | E8: ='Paramètres'!$C$17 | F8: ='Paramètres'!$C$7 | G8: =(($C8*('Paramètres'!$C$21/5)*$D8)/12)*(1-(1-(1-$E8^(1/12)))^37)/(1-$E8^(1/12)) | H8: =G8*$F8 | I8: =(((($C8*('Paramètres'!$C$21/5)*$D8)/12)/(1-$E8^(1/12)))*(1-(1-(1-(1-$E8^(1/12)))^37)/(37*(1-$E8^(1/12))))*$F8+(($C8*('Paramètres'!$C$21/5)*$D8)/12)*'Paramètres'!$C$8)*'Paramètres'!$C$37
B9: Optimiste | C9: 1.5 | D9: 0.6 | E9: 0.9 | F9: 185 | G9: =(($C9*('Paramètres'!$C$21/5)*$D9)/12)*(1-(1-(1-$E9^(1/12)))^37)/(1-$E9^(1/12)) | H9: =G9*$F9 | I9: =(((($C9*('Paramètres'!$C$21/5)*$D9)/12)/(1-$E9^(1/12)))*(1-(1-(1-(1-$E9^(1/12)))^37)/(37*(1-$E9^(1/12))))*$F9+(($C9*('Paramètres'!$C$21/5)*$D9)/12)*'Paramètres'!$C$8)*'Paramètres'!$C$37
B10: Agressif | C10: 2.5 | D10: 0.65 | E10: 0.92 | F10: 231 | G10: =(($C10*('Paramètres'!$C$21/5)*$D10)/12)*(1-(1-(1-$E10^(1/12)))^37)/(1-$E10^(1/12)) | H10: =G10*$F10 | I10: =(((($C10*('Paramètres'!$C$21/5)*$D10)/12)/(1-$E10^(1/12)))*(1-(1-(1-(1-$E10^(1/12)))^37)/(37*(1-$E10^(1/12))))*$F10+(($C10*('Paramètres'!$C$21/5)*$D10)/12)*'Paramètres'!$C$8)*'Paramètres'!$C$37
B33: Les cellules à fond crème sont modifiables : chaque scénario est indépendant.
B34: La ligne « Référence » recopie automatiquement la feuille Paramètres.
